nornir_tests/__init__.py
nornir_tests/plugins/__init__.py
nornir_tests/plugins/functions/__init__.py
nornir_tests/plugins/functions/print_result.py
nornir_tests/plugins/tasks/__init__.py
nornir_tests/plugins/tasks/wrap_task.py
nornir_tests/plugins/tests/__init__.py
nornir_tests/plugins/tests/callback.py
nornir_tests/plugins/tests/jpath.py
nornir_tests/plugins/tests/loop.py
nornir_tests/plugins/tests/regexp.py
nornir_tests/plugins/tests/shorten.py
nornir_tests/plugins/tests/test.py
nornir_tests/plugins/tests/timing.py
nornir_tests/plugins/tests/until.py
nornir_tests/plugins/tests/when.py
nornir_tests/plugins/tests/xpath.py
nornir_tests-1.0.0.dist-info/METADATA
nornir_tests-1.0.0.dist-info/WHEEL
nornir_tests-1.0.0.dist-info/top_level.txt
nornir_tests-1.0.0.dist-info/RECORD
