Metadata-Version: 2.4
Name: nornir-tests
Version: 1.0.0
Summary: Testing extension for Nornir
Requires-Python: <4.0,>=3.10
Requires-Dist: assertpy>=1.1
Requires-Dist: jsonpath-ng>=1.7.0
Requires-Dist: lxml>=5.4.0
Requires-Dist: nornir>=3.5.0
Requires-Dist: rich>=14.0.0
Requires-Dist: wrapt>=1.17.2
